bitcoin_lite/__init__.py
bitcoin_lite/analytics.py
bitcoin_lite/dashboard.js
bitcoin_lite/database.py
bitcoin_lite/datagenerator.py
bitcoin_lite/transaction.pyx
bitcoin_lite-0.1.5.dist-info/WHEEL
bitcoin_lite-0.1.5.dist-info/METADATA
bitcoin_lite-0.1.5.dist-info/RECORD
