Metadata-Version: 2.1
Name: bitcoin-lite
Version: 0.1.5
Summary: A lightweight Bitcoin transaction system using Cython
Home-page: https://github.com/danymukesha/bitcoin-lite
Keywords: bitcoin-lite,blockchain,danymukesha
Author: Dany Mukesha
Author-email: danymukesha@gmail.com
Requires-Python: >=3.10,<4.0
Classifier: Programming Language :: Python :: 3
Classifier: Programming Language :: Python :: 3.10
Requires-Dist: Cython (>=3.0.11,<4.0.0)
